transtab/__init__.py
transtab/constants.py
transtab/dataset.py
transtab/evaluator.py
transtab/modeling_transtab.py
transtab/trainer.py
transtab/trainer_utils.py
transtab/transtab.py
transtab-0.0.5.dist-info/LICENSE
transtab-0.0.5.dist-info/METADATA
transtab-0.0.5.dist-info/WHEEL
transtab-0.0.5.dist-info/top_level.txt
transtab-0.0.5.dist-info/RECORD
