Metadata-Version: 2.1
Name: transtab
Version: 0.0.5
Summary: A flexible tabular prediction model that handles variable-column input tables.
Home-page: https://github.com/RyanWangZf/transtab
Author: Zifeng Wang
Author-email: zifengw2@illinois.edu
Keywords: tabular data,machine learning,data mining,data science
Classifier: Programming Language :: Python :: 3
Classifier: Programming Language :: Python :: 3.7
Classifier: Programming Language :: Python :: 3.8
Classifier: Programming Language :: Python :: 3.9
Classifier: License :: OSI Approved :: BSD License
Classifier: Operating System :: OS Independent
License-File: LICENSE
Requires-Dist: loguru
Requires-Dist: numpy
Requires-Dist: scikit-learn
Requires-Dist: setuptools
Requires-Dist: transformers
Requires-Dist: tqdm
Requires-Dist: pandas (>=1.3.0)
Requires-Dist: openml (>=0.10.0)
